MANIFEST.in
README.md
README.txt
setup.cfg
setup.py
SwampDragon.egg-info/PKG-INFO
SwampDragon.egg-info/SOURCES.txt
SwampDragon.egg-info/dependency_links.txt
SwampDragon.egg-info/entry_points.txt
SwampDragon.egg-info/requires.txt
SwampDragon.egg-info/top_level.txt
deprecated_runtests/__init__.py
deprecated_runtests/settings.py
swampdragon/__init__.py
swampdragon/default_settings.py
swampdragon/message_format.py
swampdragon/model_tools.py
swampdragon/models.py
swampdragon/paginator.py
swampdragon/permissions.py
swampdragon/route_handler.py
swampdragon/same_origin.py
swampdragon/settings_provider.py
swampdragon/swampdragon_server.py
swampdragon/app_templates/sd_settings.py
swampdragon/app_templates/server.py
swampdragon/connections/__init__.py
swampdragon/connections/mock_connection.py
swampdragon/connections/sockjs_connection.py
swampdragon/core/__init__.py
swampdragon/management/__init__.py
swampdragon/management/commands/__init__.py
swampdragon/management/commands/runsd.py
swampdragon/pubsub_providers/__init__.py
swampdragon/pubsub_providers/base_provider.py
swampdragon/pubsub_providers/channel_filters.py
swampdragon/pubsub_providers/channel_utils.py
swampdragon/pubsub_providers/data_publisher.py
swampdragon/pubsub_providers/mock_publisher.py
swampdragon/pubsub_providers/mock_sub_provider.py
swampdragon/pubsub_providers/model_channel_builder.py
swampdragon/pubsub_providers/model_publisher.py
swampdragon/pubsub_providers/publisher_factory.py
swampdragon/pubsub_providers/redis_publisher.py
swampdragon/pubsub_providers/redis_settings.py
swampdragon/pubsub_providers/redis_sub_provider.py
swampdragon/pubsub_providers/subscriber_factory.py
swampdragon/serializers/__init__.py
swampdragon/serializers/field_deserializers.py
swampdragon/serializers/field_serializers.py
swampdragon/serializers/model_serializer.py
swampdragon/serializers/object_map.py
swampdragon/serializers/serializer.py
swampdragon/serializers/serializer_importer.py
swampdragon/serializers/serializer_tools.py
swampdragon/serializers/validation.py
swampdragon/sessions/__init__.py
swampdragon/sessions/redis_session_store.py
swampdragon/sessions/session_store.py
swampdragon/sessions/sessions.py
