Metadata-Version: 1.1
Name: SwampDragon
Version: 0.4.2
Summary: SwampDragon is a powerful platform making it easy to build real time web applications, combining the power of Django and Tornado
Home-page: http://swampdragon.net
Author: Jonas Hagstedt
Author-email: hagstedt@gmail.com
License: BSD
Keywords: SwampDragon,websockets,realtime,sockjs,django,tornado,framework
Platform: UNKNOWN
Classifier: Development Status :: 4 - Beta
Classifier: License :: OSI Approved :: BSD License
Classifier: Programming Language :: Python :: 2.7
Classifier: Programming Language :: Python :: 3
Classifier: Programming Language :: Python :: 3.3
Classifier: Programming Language :: Python :: 3.4
